buffer.v
module buffer (
    input wire inp,
    input wire clk,
    output reg out
);

    always @(posedge clk) begin
        out <= inp;         // Transfer input to output on positive clock edge.
    end

endmodule

buffer_tb.v
`timescale 1ps/1ps

module buffer_tb;

reg clk;
reg inp;
wire out;

buffer uut (
    .clk(clk),
    .inp(inp),
    .out(out)
);

initial begin
    clk = 0;
    inp = 0;
end

//Clock generation
always #5 clk = ~clk;       // Toggle clock every 5 time units

initial begin
    #10 inp = 1;
    #20 inp = 0;

    #40 inp = 1;
    #60 inp = 0;

    // End simulation
    #100;
    $finish;
end

initial begin
    $monitor("Time: %0d, input: %b, output: %b ", $time, inp, out);
    $dumpfile("buffer_tb.vcd");
    $dumpvars(0,buffer_tb);
end

endmodule

buffer_tb.vcd
$date
	Sat Oct 26 15:23:01 2024
$end
$version
	Icarus Verilog
$end
$timescale
	1ps
$end
$scope module buffer_tb $end
$var wire 1 ! out $end
$var reg 1 " clk $end
$var reg 1 # inp $end
$scope module uut $end
$var wire 1 " clk $end
$var wire 1 # inp $end
$var reg 1 ! out $end
$upscope $end
$upscope $end
$enddefinitions $end
#0
$dumpvars
0#
0"
x!
$end
#5
0!
1"
#10
0"
1#
#15
1!
1"
#20
0"
#25
1"
#30
0"
0#
#35
0!
1"
#40
0"
#45
1"
#50
0"
#55
1"
#60
0"
#65
1"
#70
0"
1#
#75
1!
1"
#80
0"
#85
1"
#90
0"
#95
1"
#100
0"
#105
1"
#110
0"
#115
1"
#120
0"
#125
1"
#130
0"
0#
#135
0!
1"
